<?xml version="1.0" encoding="windows-1250" ?>

<string_table>

	<string id="agr_und_first_task_1">
		<text>Poszukiwanie Informacji: ZnajdŸ informacje o Strie³oku</text>
	</string>
	<string id="agr_und_first_task_2">
		<text>Szkir zawsze szuka sposobu na unikniêcie wêdrówek ze mn¹. Po co zosta³ zabrany do oddzia³u, skoro ca³y czas siê miga? Coœ jest nie tak, muszê siê dowiedzieæ.</text>
	</string>
	<string id="agr_und_first_task_3">
		<text>Poszukiwanie Informacji: Poka¿ notatkê Szkirowi</text>
	</string>
	<string id="agr_und_first_task_4">
		<text>Tu jest napisane: "Idê do elektrowni j¹drowej w Czarnobylu" i mo¿na siê tam dostaæ tylko przez Czerwony Las. Okazuje siê, ¿e Szkir post¹pi³ bardzo g³upio, przechodz¹c na Agroprom. Jeœli kontrakt siê nie powiedzie z jego winy, logiczne bêdzie zabicie go.</text>
	</string>


</string_table>
